CHANGES.rst
CONTRIBUTORS.rst
DEVELOP.rst
LICENSE.rst
MANIFEST.in
README.rst
setup.cfg
setup.py
docs/conf.py
docs/index.rst
src/collective/__init__.py
src/collective.restapi.facetedsearch.egg-info/PKG-INFO
src/collective.restapi.facetedsearch.egg-info/SOURCES.txt
src/collective.restapi.facetedsearch.egg-info/dependency_links.txt
src/collective.restapi.facetedsearch.egg-info/entry_points.txt
src/collective.restapi.facetedsearch.egg-info/namespace_packages.txt
src/collective.restapi.facetedsearch.egg-info/not-zip-safe
src/collective.restapi.facetedsearch.egg-info/requires.txt
src/collective.restapi.facetedsearch.egg-info/top_level.txt
src/collective/restapi/__init__.py
src/collective/restapi/facetedsearch/__init__.py
src/collective/restapi/facetedsearch/configure.zcml
src/collective/restapi/facetedsearch/interfaces.py
src/collective/restapi/facetedsearch/permissions.zcml
src/collective/restapi/facetedsearch/setuphandlers.py
src/collective/restapi/facetedsearch/testing.py
src/collective/restapi/facetedsearch/api/__init__.py
src/collective/restapi/facetedsearch/api/configure.zcml
src/collective/restapi/facetedsearch/api/services/__init__.py
src/collective/restapi/facetedsearch/api/services/configure.zcml
src/collective/restapi/facetedsearch/api/services/faceted_search/__init__.py
src/collective/restapi/facetedsearch/api/services/faceted_search/configure.zcml
src/collective/restapi/facetedsearch/api/services/faceted_search/get.py
src/collective/restapi/facetedsearch/api/services/faceted_search/groupByModifiers.py
src/collective/restapi/facetedsearch/api/services/faceted_search/handler.py
src/collective/restapi/facetedsearch/browser/__init__.py
src/collective/restapi/facetedsearch/browser/configure.zcml
src/collective/restapi/facetedsearch/browser/overrides/.gitkeep
src/collective/restapi/facetedsearch/browser/static/.gitkeep
src/collective/restapi/facetedsearch/locales/README.rst
src/collective/restapi/facetedsearch/locales/__init__.py
src/collective/restapi/facetedsearch/locales/collective.restapi.facetedsearch.pot
src/collective/restapi/facetedsearch/locales/update.py
src/collective/restapi/facetedsearch/locales/update.sh
src/collective/restapi/facetedsearch/locales/en/LC_MESSAGES/collective.restapi.facetedsearch.mo
src/collective/restapi/facetedsearch/locales/en/LC_MESSAGES/collective.restapi.facetedsearch.po
src/collective/restapi/facetedsearch/profiles/default/browserlayer.xml
src/collective/restapi/facetedsearch/profiles/default/catalog.xml
