Metadata-Version: 2.1
Name: collective.restapi.facetedsearch
Version: 1.0.2
Summary: An add-on for Plone and plone.restapi providing a extended search service
Home-page: https://git.saw-leipzig.de/muellers/collective.restapi.facetedsearch
Author: muellers
Author-email: muellers@saw-leipzig.de
License: GPL version 2
Project-URL: PyPI, https://pypi.python.org/pypi/collective.restapi.facetedsearch
Project-URL: Source, https://git.saw-leipzig.de/muellers/collective.restapi.facetedsearch.git
Project-URL: Tracker, https://git.saw-leipzig.de/muellers/collective.restapi.facetedsearch/-/issues
Keywords: Python Plone
Platform: UNKNOWN
Classifier: Environment :: Web Environment
Classifier: Framework :: Plone
Classifier: Framework :: Plone :: Addon
Classifier: Framework :: Plone :: 5.2
Classifier: Programming Language :: Python
Classifier: Programming Language :: Python :: 2.7
Classifier: Programming Language :: Python :: 3.6
Classifier: Programming Language :: Python :: 3.7
Classifier: Operating System :: OS Independent
Classifier: License :: OSI Approved :: GNU General Public License v2 (GPLv2)
Requires-Python: ==2.7, >=3.6
Provides-Extra: test
